pin_plot.py
pinplot-0.1.1.dist-info/DESCRIPTION.rst
pinplot-0.1.1.dist-info/METADATA
pinplot-0.1.1.dist-info/RECORD
pinplot-0.1.1.dist-info/WHEEL
pinplot-0.1.1.dist-info/metadata.json
pinplot-0.1.1.dist-info/top_level.txt
