Metadata-Version: 2.0
Name: pinplot
Version: 0.1.1
Summary: A simple tool for plotting pins in lattice of a nuclear reactor.
Home-page: https://github.com/Neophyliam/pinplot
Author: neophyliam
Author-email: neophyliam@gmail.com
License: UNKNOWN
Platform: UNKNOWN
Classifier: Programming Language :: Python :: 3
Classifier: License :: OSI Approved :: MIT License
Classifier: Operating System :: OS Independent
Requires-Dist: matplotlib
Requires-Dist: numpy
